imvdb/Imath-3_1.dll
imvdb/__init__.py
imvdb/__main__.py
imvdb/blosc.dll
imvdb/grid.py
imvdb/image.py
imvdb/lz4.dll
imvdb/openvdb.dll
imvdb/tbb12.dll
imvdb/vdb.cp310-win_amd64.pyd
imvdb/zlib1.dll
imvdb/zstd.dll
imvdb-1.0.0.dist-info/METADATA
imvdb-1.0.0.dist-info/WHEEL
imvdb-1.0.0.dist-info/top_level.txt
imvdb-1.0.0.dist-info/RECORD
