Metadata-Version: 2.1
Name: imvdb
Version: 1.0.0
Summary: volumetric image in openvdb format
Author-email: doidio <88172828@qq.com>
License: MIT
Project-URL: Homepage, https://github.com/doidio/imvdb
Project-URL: Bug Tracker, https://github.com/doidio/imvdb/issues
Keywords: one,two
Classifier: Programming Language :: Python :: 3
Requires-Python: ==3.10.*
Requires-Dist: click
Requires-Dist: numpy
Requires-Dist: itk
